Metadata-Version: 2.1
Name: fatcat
Version: 0.0.5
Summary: A python package for FatCat Hosting
Home-page: https://github.com/INfoUpgraders/fatcat
Author: INfoUpgraders
License: MIT
Project-URL: Documentation, https://fatcat.readthedocs.io/en/latest/
Project-URL: Issue tracker, https://github.com/INfoUpgraders/fatcat/issues
Platform: UNKNOWN
Classifier: Development Status :: 5 - Production/Stable
Classifier: License :: OSI Approved :: MIT License
Classifier: Intended Audience :: Developers
Classifier: Natural Language :: English
Classifier: Operating System :: OS Independent
Classifier: Programming Language :: Python :: 3.6
Classifier: Programming Language :: Python :: 3.7
Classifier: Programming Language :: Python :: 3.8
Classifier: Topic :: Internet
Classifier: Topic :: Software Development :: Libraries
Classifier: Topic :: Software Development :: Libraries :: Python Modules
Classifier: Topic :: Utilities
Requires-Python: >=3.6
Provides-Extra: docs
